meta_metadata_rules/__init__.py
meta_metadata_rules/admin.py
meta_metadata_rules/apps.py
meta_metadata_rules/tests.py
meta_metadata_rules/views.py
meta_metadata_rules-0.1.1.dist-info/AUTHORS
meta_metadata_rules-0.1.1.dist-info/LICENSE
meta_metadata_rules-0.1.1.dist-info/METADATA
meta_metadata_rules-0.1.1.dist-info/WHEEL
meta_metadata_rules-0.1.1.dist-info/top_level.txt
meta_metadata_rules-0.1.1.dist-info/RECORD
