Metadata-Version: 2.1
Name: meta-metadata-rules
Version: 0.1.1
Summary: Metadata rules for meta/edc project
Home-page: https://github.com/meta-trial/meta-metadata-rules
Author: Erik van Widenfelt
Author-email: ew2789@gmail.com
License: GPL license, see LICENSE
Keywords: django edc clinicedc meta
Platform: UNKNOWN
Classifier: Environment :: Web Environment
Classifier: Framework :: Django
Classifier: Intended Audience :: Developers
Classifier: Intended Audience :: Science/Research
Classifier: License :: OSI Approved :: GNU General Public License v3 (GPLv3)
Classifier: Operating System :: OS Independent
Classifier: Programming Language :: Python :: 3.7
Classifier: Topic :: Internet :: WWW/HTTP
Classifier: Topic :: Internet :: WWW/HTTP :: Dynamic Content
Requires-Python: >=3.7
Requires-Dist: edc-action-item
Requires-Dist: edc-metadata
Requires-Dist: edc-metadata-rules
Requires-Dist: edc-offstudy
Requires-Dist: edc-constants
Requires-Dist: edc-reportable
